openadapt_ml/__init__.py
openadapt_ml/config.py
openadapt_ml/baselines/__init__.py
openadapt_ml/baselines/adapter.py
openadapt_ml/baselines/cli.py
openadapt_ml/baselines/config.py
openadapt_ml/baselines/parser.py
openadapt_ml/baselines/prompts.py
openadapt_ml/benchmarks/__init__.py
openadapt_ml/benchmarks/agent.py
openadapt_ml/benchmarks/azure.py
openadapt_ml/benchmarks/azure_ops_tracker.py
openadapt_ml/benchmarks/cli.py
openadapt_ml/benchmarks/trace_export.py
openadapt_ml/benchmarks/viewer.py
openadapt_ml/benchmarks/vm_monitor.py
openadapt_ml/benchmarks/waa_deploy/Dockerfile
openadapt_ml/benchmarks/waa_deploy/__init__.py
openadapt_ml/benchmarks/waa_deploy/api_agent.py
openadapt_ml/benchmarks/waa_deploy/start_waa_server.bat
openadapt_ml/cloud/__init__.py
openadapt_ml/cloud/azure_inference.py
openadapt_ml/cloud/lambda_labs.py
openadapt_ml/cloud/local.py
openadapt_ml/cloud/ssh_tunnel.py
openadapt_ml/datasets/__init__.py
openadapt_ml/datasets/next_action.py
openadapt_ml/evals/__init__.py
openadapt_ml/evals/grounding.py
openadapt_ml/evals/plot_eval_metrics.py
openadapt_ml/evals/trajectory_matching.py
openadapt_ml/experiments/demo_prompt/__init__.py
openadapt_ml/experiments/demo_prompt/format_demo.py
openadapt_ml/experiments/demo_prompt/run_experiment.py
openadapt_ml/experiments/demo_prompt/results/experiment_20251231_002125.json
openadapt_ml/experiments/demo_prompt/results/experiment_n30_20251231_165958.json
openadapt_ml/experiments/demo_prompt/results/multistep_20251231_025051.json
openadapt_ml/experiments/representation_shootout/__init__.py
openadapt_ml/experiments/representation_shootout/conditions.py
openadapt_ml/experiments/representation_shootout/config.py
openadapt_ml/experiments/representation_shootout/evaluator.py
openadapt_ml/experiments/representation_shootout/runner.py
openadapt_ml/experiments/waa_demo/__init__.py
openadapt_ml/experiments/waa_demo/demos.py
openadapt_ml/experiments/waa_demo/runner.py
openadapt_ml/experiments/waa_demo/tasks.py
openadapt_ml-0.2.2.dist-info/METADATA
openadapt_ml-0.2.2.dist-info/WHEEL
openadapt_ml-0.2.2.dist-info/licenses/LICENSE
openadapt_ml-0.2.2.dist-info/RECORD
