Metadata-Version: 2.4
Name: openadapt-ml
Version: 0.2.2
Summary: Model-agnostic, domain-agnostic ML engine for GUI automation agents
Project-URL: Homepage, https://github.com/OpenAdaptAI/openadapt-ml
Project-URL: Repository, https://github.com/OpenAdaptAI/openadapt-ml
Project-URL: Documentation, https://github.com/OpenAdaptAI/openadapt-ml/tree/main/docs
Author-email: "MLDSAI Inc." <richard@mldsai.com>
License-Expression: MIT
License-File: LICENSE
Keywords: agents,automation,fine-tuning,gui,ml,vision-language-models,vlm
Classifier: Development Status :: 3 - Alpha
Classifier: Intended Audience :: Developers
Classifier: License :: OSI Approved :: MIT License
Classifier: Programming Language :: Python :: 3
Classifier: Programming Language :: Python :: 3.10
Classifier: Programming Language :: Python :: 3.11
Classifier: Programming Language :: Python :: 3.12
Classifier: Topic :: Scientific/Engineering :: Artificial Intelligence
Classifier: Topic :: Software Development :: Libraries :: Python Modules
Requires-Python: >=3.10
Requires-Dist: azure-ai-ml>=1.30.0
Requires-Dist: azure-identity>=1.25.1
Requires-Dist: bitsandbytes>=0.41.0
Requires-Dist: click>=8.1.0
Requires-Dist: google-generativeai>=0.8.5
Requires-Dist: matplotlib>=3.10.7
Requires-Dist: openadapt-capture>=0.1.0
Requires-Dist: peft>=0.18.0
Requires-Dist: pillow>=12.0.0
Requires-Dist: pyautogui>=0.9.54
Requires-Dist: pydantic-settings>=2.0.0
Requires-Dist: pytest>=9.0.2
Requires-Dist: pyyaml>=6.0.3
Requires-Dist: torch>=2.9.1
Requires-Dist: torchvision>=0.24.1
Requires-Dist: transformers>=4.57.3
Provides-Extra: api
Requires-Dist: anthropic>=0.40.0; extra == 'api'
Requires-Dist: openai>=1.0.0; extra == 'api'
Requires-Dist: pydantic-settings>=2.0.0; extra == 'api'
Provides-Extra: azure
Requires-Dist: azure-ai-ml>=1.0.0; extra == 'azure'
Requires-Dist: azure-identity>=1.0.0; extra == 'azure'
Provides-Extra: benchmarks
Requires-Dist: openadapt-evals>=0.1.1; extra == 'benchmarks'
Provides-Extra: dev
Requires-Dist: pytest>=9.0.0; extra == 'dev'
Requires-Dist: ruff>=0.1.0; extra == 'dev'
Provides-Extra: lambda-labs
Requires-Dist: requests>=2.28.0; extra == 'lambda-labs'
Provides-Extra: parquet
Requires-Dist: pyarrow>=14.0.0; extra == 'parquet'
Provides-Extra: training
Requires-Dist: datasets>=2.18.0; extra == 'training'
Requires-Dist: trl>=0.12.0; extra == 'training'
